SEIR/__init__.py
SEIR/cli.py
SEIR/seir.py
SEIR/visualization.py
SEIR/model_configs/basic
SEIR/model_configs/finland
SEIR/model_configs/finland_with_restrictions
SEIR/parser/__init__.py
SEIR/parser/config_file_parser.py
SEIR/parser/restrictions_section_parser.py
SEIR-0.2.3.dist-info/AUTHORS.rst
SEIR-0.2.3.dist-info/LICENSE
SEIR-0.2.3.dist-info/METADATA
SEIR-0.2.3.dist-info/WHEEL
SEIR-0.2.3.dist-info/entry_points.txt
SEIR-0.2.3.dist-info/top_level.txt
SEIR-0.2.3.dist-info/RECORD
