Metadata-Version: 2.1
Name: SEIR
Version: 0.2.3
Summary: SEIR modelling of covid19
Home-page: https://github.com/covid19-bh-biostats/seir
Author: Biostats team
Author-email: lukas.heumos@posteo.net
License: MIT
Keywords: SEIR
Platform: UNKNOWN
Classifier: Development Status :: 3 - Alpha
Classifier: Environment :: Console
Classifier: Intended Audience :: Developers
Classifier: License :: OSI Approved :: MIT License
Classifier: Natural Language :: English
Classifier: Programming Language :: Python :: 3
Classifier: Programming Language :: Python :: 3.7
Classifier: Programming Language :: Python :: 3.8
Requires-Python: >=3.5
Requires-Dist: click
Requires-Dist: numpy
Requires-Dist: scipy (>=1.4.0)
Requires-Dist: pandas
Requires-Dist: matplotlib
